LICENSE
MANIFEST.in
README.rst
setup.py
bin/grab_oncall.py
pygerduty/__init__.py
pygerduty/version.py
pygerduty_py3.egg-info/PKG-INFO
pygerduty_py3.egg-info/SOURCES.txt
pygerduty_py3.egg-info/dependency_links.txt
pygerduty_py3.egg-info/top_level.txt