Metadata-Version: 1.1
Name: pygerduty-py3
Version: 0.28.2
Summary: Python Client Library for PagerDuty's REST API
Home-page: https://github.com/cardforcoin/pygerduty
Author: Gary M. Josack
Author-email: gary@dropbox.com
License: MIT
Platform: UNKNOWN
Classifier: Programming Language :: Python
Classifier: Topic :: Software Development
Classifier: Topic :: Software Development :: Libraries
Classifier: Topic :: Software Development :: Libraries :: Python Modules
